<?xml version="1.0" encoding="utf-8"?>
<abapGit version="v1.0.0" serializer="LCL_OBJECT_SIA1" serializer_version="v1.0.0">
 <asx:abap xmlns:asx="http://www.sap.com/abapxml" version="1.0">
  <asx:values>
   <SIA1>
    <MAIN_OBJECT>
     <DESCRIPTION>Custom App Catalog for FI</DESCRIPTION>
     <LANGUAGE>EN</LANGUAGE>
     <ABAP_LANGU_VERSION>5</ABAP_LANGU_VERSION>
    </MAIN_OBJECT>
    <OBJECT_VISIBILITY>
     <IS_BU_CATALOG_TYPE_VISIBLE>X</IS_BU_CATALOG_TYPE_VISIBLE>
     <DEFAULT_BU_CATALOG_TYPE>A</DEFAULT_BU_CATALOG_TYPE>
     <IS_SCOPE_DEPENDENT_VISIBLE>X</IS_SCOPE_DEPENDENT_VISIBLE>
     <IS_SCOPE_DEPENDENT_EDITABLE>X</IS_SCOPE_DEPENDENT_EDITABLE>
     <IS_RESTRICTABLE_EDITABLE>X</IS_RESTRICTABLE_EDITABLE>
    </OBJECT_VISIBILITY>
    <BU_CATALOG_ID>Z_CUST_CATALOG_FI</BU_CATALOG_ID>
    <BU_CATALOG_TYPE>A</BU_CATALOG_TYPE>
    <SCOPE_STATUS>3</SCOPE_STATUS>
    <SCOPE_STATUS_TEXT>On</SCOPE_STATUS_TEXT>
    <CATALOG_ID>Z_CUST_CATALOG_FI</CATALOG_ID>
    <AGR_NAME>Z_CUST_CATALOG_FI</AGR_NAME>
    <ABAP_LANGUAGE_VERSION>5</ABAP_LANGUAGE_VERSION>
    <BUCAPP>
     <item>
      <BU_CATALOG_APP_ID>Z_CUST_CATALOG_FI_0004</BU_CATALOG_APP_ID>
      <BU_CATALOG_ID>Z_CUST_CATALOG_FI</BU_CATALOG_ID>
      <APP_ID>Z_IAM_DEBIT_NOTE_PRINT_EXT</APP_ID>
      <ROLE_CHANGE>A</ROLE_CHANGE>
      <CATALOG_CHANGE>A</CATALOG_CHANGE>
      <GROUP_CHANGE>A</GROUP_CHANGE>
      <CHIP_ID>X-SAP-UI2-PAGE:X-SAP-UI2-CATALOGPAGE:Z_CUST_CATALOG_FI:1Q6E6JA5GXDX0YO1UURF0VWXS</CHIP_ID>
      <ABAP_LANGUAGE_VERSION>5</ABAP_LANGUAGE_VERSION>
     </item>
     <item>
      <BU_CATALOG_APP_ID>Z_CUST_CATALOG_FI_0003</BU_CATALOG_APP_ID>
      <BU_CATALOG_ID>Z_CUST_CATALOG_FI</BU_CATALOG_ID>
      <APP_ID>Z_IAM_CREDIT_NOTE_PRINT_EXT</APP_ID>
      <ROLE_CHANGE>A</ROLE_CHANGE>
      <CATALOG_CHANGE>A</CATALOG_CHANGE>
      <GROUP_CHANGE>A</GROUP_CHANGE>
      <CHIP_ID>X-SAP-UI2-PAGE:X-SAP-UI2-CATALOGPAGE:Z_CUST_CATALOG_FI:1Q6E6JA5GXDX0YO1UE7O90L8G</CHIP_ID>
      <ABAP_LANGUAGE_VERSION>5</ABAP_LANGUAGE_VERSION>
     </item>
     <item>
      <BU_CATALOG_APP_ID>Z_CUST_CATALOG_FI_0002</BU_CATALOG_APP_ID>
      <BU_CATALOG_ID>Z_CUST_CATALOG_FI</BU_CATALOG_ID>
      <APP_ID>Z_IAM_CHQ_PRINT_EXT</APP_ID>
      <ROLE_CHANGE>A</ROLE_CHANGE>
      <CATALOG_CHANGE>A</CATALOG_CHANGE>
      <GROUP_CHANGE>A</GROUP_CHANGE>
      <CHIP_ID>X-SAP-UI2-PAGE:X-SAP-UI2-CATALOGPAGE:Z_CUST_CATALOG_FI:1Q6E6JA5GXDX0YO1TZ929YLXC</CHIP_ID>
      <ABAP_LANGUAGE_VERSION>5</ABAP_LANGUAGE_VERSION>
     </item>
     <item>
      <BU_CATALOG_APP_ID>Z_CUST_CATALOG_FI_0001</BU_CATALOG_APP_ID>
      <BU_CATALOG_ID>Z_CUST_CATALOG_FI</BU_CATALOG_ID>
      <APP_ID>Z_IAM_VEND_AGE_EXT</APP_ID>
      <ROLE_CHANGE>A</ROLE_CHANGE>
      <CATALOG_CHANGE>A</CATALOG_CHANGE>
      <GROUP_CHANGE>A</GROUP_CHANGE>
      <CHIP_ID>X-SAP-UI2-PAGE:X-SAP-UI2-CATALOGPAGE:Z_CUST_CATALOG_FI:1Q6E6JA5GXDX0YO1TC09KCPKW</CHIP_ID>
      <ABAP_LANGUAGE_VERSION>5</ABAP_LANGUAGE_VERSION>
     </item>
     <item>
      <BU_CATALOG_APP_ID>Z_CUST_CATALOG_FI_0007</BU_CATALOG_APP_ID>
      <BU_CATALOG_ID>Z_CUST_CATALOG_FI</BU_CATALOG_ID>
      <APP_ID>Z_IAM_RCM_PRINT_EXT</APP_ID>
      <ROLE_CHANGE>A</ROLE_CHANGE>
      <CATALOG_CHANGE>A</CATALOG_CHANGE>
      <GROUP_CHANGE>A</GROUP_CHANGE>
      <CHIP_ID>X-SAP-UI2-PAGE:X-SAP-UI2-CATALOGPAGE:Z_CUST_CATALOG_FI:1Q6E6JA5GXDX0YO2A4847Y4XS</CHIP_ID>
      <ABAP_LANGUAGE_VERSION>5</ABAP_LANGUAGE_VERSION>
     </item>
     <item>
      <BU_CATALOG_APP_ID>Z_CUST_CATALOG_FI_0006</BU_CATALOG_APP_ID>
      <BU_CATALOG_ID>Z_CUST_CATALOG_FI</BU_CATALOG_ID>
      <APP_ID>Z_IAM_VOUCHER_PRINT_EXT</APP_ID>
      <ROLE_CHANGE>A</ROLE_CHANGE>
      <CATALOG_CHANGE>A</CATALOG_CHANGE>
      <GROUP_CHANGE>A</GROUP_CHANGE>
      <CHIP_ID>X-SAP-UI2-PAGE:X-SAP-UI2-CATALOGPAGE:Z_CUST_CATALOG_FI:1Q6E6JA5GXDX0YO29QYKEINB4</CHIP_ID>
      <ABAP_LANGUAGE_VERSION>5</ABAP_LANGUAGE_VERSION>
     </item>
     <item>
      <BU_CATALOG_APP_ID>Z_CUST_CATALOG_FI_0005</BU_CATALOG_APP_ID>
      <BU_CATALOG_ID>Z_CUST_CATALOG_FI</BU_CATALOG_ID>
      <APP_ID>Z_IAM_PAY_ADV_EXT</APP_ID>
      <ROLE_CHANGE>A</ROLE_CHANGE>
      <CATALOG_CHANGE>A</CATALOG_CHANGE>
      <GROUP_CHANGE>A</GROUP_CHANGE>
      <CHIP_ID>X-SAP-UI2-PAGE:X-SAP-UI2-CATALOGPAGE:Z_CUST_CATALOG_FI:1Q6E6JA5GXDX0YO29GA9DEI68</CHIP_ID>
      <ABAP_LANGUAGE_VERSION>5</ABAP_LANGUAGE_VERSION>
     </item>
     <item>
      <BU_CATALOG_APP_ID>Z_CUST_CATALOG_FI_0008</BU_CATALOG_APP_ID>
      <BU_CATALOG_ID>Z_CUST_CATALOG_FI</BU_CATALOG_ID>
      <APP_ID>ZIAM_PRODUCTION_LOT_REP_EXT</APP_ID>
      <ROLE_CHANGE>A</ROLE_CHANGE>
      <CATALOG_CHANGE>A</CATALOG_CHANGE>
      <GROUP_CHANGE>A</GROUP_CHANGE>
      <CHIP_ID>X-SAP-UI2-PAGE:X-SAP-UI2-CATALOGPAGE:Z_CUST_CATALOG_FI:3WO8ZLH8JIIWY66GB3DJGFL4H</CHIP_ID>
      <ABAP_LANGUAGE_VERSION>5</ABAP_LANGUAGE_VERSION>
     </item>
     <item>
      <BU_CATALOG_APP_ID>Z_CUST_CATALOG_FI_0009</BU_CATALOG_APP_ID>
      <BU_CATALOG_ID>Z_CUST_CATALOG_FI</BU_CATALOG_ID>
      <APP_ID>ZFI_CUSTAGE_REPORT_EXT</APP_ID>
      <ROLE_CHANGE>A</ROLE_CHANGE>
      <CATALOG_CHANGE>A</CATALOG_CHANGE>
      <GROUP_CHANGE>A</GROUP_CHANGE>
      <CHIP_ID>X-SAP-UI2-PAGE:X-SAP-UI2-CATALOGPAGE:Z_CUST_CATALOG_FI:3WO8ZLH8JIIX1EN9M5EJPTUJ4</CHIP_ID>
      <ABAP_LANGUAGE_VERSION>5</ABAP_LANGUAGE_VERSION>
     </item>
    </BUCAPP>
    <PUBLISH_STATUS>p</PUBLISH_STATUS>
   </SIA1>
  </asx:values>
 </asx:abap>
</abapGit>
